seed_guard/__init__.py
seed_guard/_bip39.py
seed_guard/_bip39_compression.py
seed_guard/_bip39_encryptor.py
seed_guard/_bip39_shamir.py
seed_guard/_bip39_wordlist.py
seed_guard/_mnenomic_length.py
seed_guard/_secret_splitter.py
seed_guard/_seed_guard_impl.py
seed_guard/_share_encoder.py
seed_guard-0.1.2.dist-info/METADATA
seed_guard-0.1.2.dist-info/WHEEL
seed_guard-0.1.2.dist-info/licenses/LICENSE
seed_guard-0.1.2.dist-info/RECORD
