Metadata-Version: 2.4
Name: seed_guard
Version: 0.1.2
Summary: Secure seed phrase backup using Shamir's Secret Sharing
Project-URL: Homepage, https://github.com/RyBut/seed-guard
Project-URL: Bug Tracker, https://github.com/RyBut/seed-guard/issues
Author-email: WaxDevil <SeedGuard@mail.rybot.ca>
License-File: LICENSE
Classifier: License :: OSI Approved :: MIT License
Classifier: Operating System :: OS Independent
Classifier: Programming Language :: Python :: 3
Requires-Python: >=3.8
Requires-Dist: cryptography>=36.0.0
